odoo/addons/maintenance_request_stage_transition/README.rst
odoo/addons/maintenance_request_stage_transition/__init__.py
odoo/addons/maintenance_request_stage_transition/__manifest__.py
odoo/addons/maintenance_request_stage_transition/i18n/es.po
odoo/addons/maintenance_request_stage_transition/i18n/it.po
odoo/addons/maintenance_request_stage_transition/i18n/maintenance_request_stage_transition.pot
odoo/addons/maintenance_request_stage_transition/i18n/pt_BR.po
odoo/addons/maintenance_request_stage_transition/models/__init__.py
odoo/addons/maintenance_request_stage_transition/models/maintenance_request.py
odoo/addons/maintenance_request_stage_transition/models/maintenance_stage.py
odoo/addons/maintenance_request_stage_transition/readme/CONTRIBUTORS.rst
odoo/addons/maintenance_request_stage_transition/readme/DESCRIPTION.rst
odoo/addons/maintenance_request_stage_transition/readme/USAGE.rst
odoo/addons/maintenance_request_stage_transition/static/description/icon.png
odoo/addons/maintenance_request_stage_transition/static/description/index.html
odoo/addons/maintenance_request_stage_transition/tests/__init__.py
odoo/addons/maintenance_request_stage_transition/tests/test_flow.py
odoo/addons/maintenance_request_stage_transition/views/maintenance_request.xml
odoo/addons/maintenance_request_stage_transition/views/maintenance_stage.xml
odoo12_addon_maintenance_request_stage_transition-12.0.1.0.0.99.dev11.dist-info/METADATA
odoo12_addon_maintenance_request_stage_transition-12.0.1.0.0.99.dev11.dist-info/WHEEL
odoo12_addon_maintenance_request_stage_transition-12.0.1.0.0.99.dev11.dist-info/top_level.txt
odoo12_addon_maintenance_request_stage_transition-12.0.1.0.0.99.dev11.dist-info/RECORD
