Metadata-Version: 2.1
Name: odoo12-addon-maintenance-request-stage-transition
Version: 12.0.1.0.0.99.dev11
Summary: Manage transition visibility and management between stages
Home-page: https://github.com/OCA/maintenance
Author: Creu Blanca,Odoo Community Association (OCA)
Author-email: support@odoo-community.org
License: AGPL-3
Platform: UNKNOWN
Classifier: Programming Language :: Python
Classifier: Framework :: Odoo
Classifier: Framework :: Odoo :: 12.0
Classifier: License :: OSI Approved :: GNU Affero General Public License v3
Requires-Python: >=3.5
Requires-Dist: odoo <12.1dev,>=12.0a
